aspose/svg/__init__.pyi
aspose/svg/builder/__init__.pyi
aspose/svg/collections/__init__.pyi
aspose/svg/converters/__init__.pyi
aspose/svg/datatypes/__init__.pyi
aspose/svg/diagnostics/__init__.pyi
aspose/svg/dom/__init__.pyi
aspose/svg/dom/attributes/__init__.pyi
aspose/svg/dom/canvas/__init__.pyi
aspose/svg/dom/css/__init__.pyi
aspose/svg/dom/events/__init__.pyi
aspose/svg/dom/mutations/__init__.pyi
aspose/svg/dom/traversal/__init__.pyi
aspose/svg/dom/traversal/filters/__init__.pyi
aspose/svg/dom/views/__init__.pyi
aspose/svg/dom/xpath/__init__.pyi
aspose/svg/drawing/__init__.pyi
aspose/svg/drawing/skiasharp/__init__.pyi
aspose/svg/events/__init__.pyi
aspose/svg/filters/__init__.pyi
aspose/svg/imagevectorization/__init__.pyi
aspose/svg/io/__init__.pyi
aspose/svg/net/__init__.pyi
aspose/svg/net/headers/__init__.pyi
aspose/svg/net/messagefilters/__init__.pyi
aspose/svg/net/messagehandlers/__init__.pyi
aspose/svg/paths/__init__.pyi
aspose/svg/rendering/__init__.pyi
aspose/svg/rendering/devices/__init__.pyi
aspose/svg/rendering/fonts/__init__.pyi
aspose/svg/rendering/image/__init__.pyi
aspose/svg/rendering/pdf/__init__.pyi
aspose/svg/rendering/pdf/encryption/__init__.pyi
aspose/svg/rendering/styles/__init__.pyi
aspose/svg/rendering/styles/paintservers/__init__.pyi
aspose/svg/rendering/xps/__init__.pyi
aspose/svg/saving/__init__.pyi
aspose/svg/saving/resourcehandlers/__init__.pyi
aspose/svg/services/__init__.pyi
aspose/svg/toolkit/__init__.pyi
aspose/svg/toolkit/optimizers/__init__.pyi
aspose/svg/window/__init__.pyi
aspose/__init__.py
aspose/pycore.cp310-win32.pyd
aspose/pycore.cp311-win32.pyd
aspose/pycore.cp36-win32.pyd
aspose/pycore.cp37-win32.pyd
aspose/pycore.cp38-win32.pyd
aspose/pycore.cp39-win32.pyd
aspose/pydrawing.cp310-win32.pyd
aspose/pydrawing.cp311-win32.pyd
aspose/pydrawing.cp36-win32.pyd
aspose/pydrawing.cp37-win32.pyd
aspose/pydrawing.cp38-win32.pyd
aspose/pydrawing.cp39-win32.pyd
aspose/pygc.cp310-win32.pyd
aspose/pygc.cp311-win32.pyd
aspose_svg-24.5.0.dist-info/METADATA
aspose_svg-24.5.0.dist-info/WHEEL
aspose_svg-24.5.0.dist-info/entry_points.txt
aspose_svg-24.5.0.dist-info/top_level.txt
aspose_svg-24.5.0.dist-info/RECORD
