Metadata-Version: 2.1
Name: aspose-svg
Version: 24.5.0
Summary: Aspose.SVG for Python via .NET enables creating, editing, rendering, and converting SVGs to formats like PNG, PDF, and more, excelling in image vectorization. Perfect for developing SVG tools.
Home-page: https://products.aspose.com/svg/python-net/
Author: Aspose
License: UNKNOWN
Project-URL: Docs, https://docs.aspose.com/svg/python-net/
Project-URL: Release Notes, https://releases.aspose.com/svg/python/release-notes/2024/aspose-svg-for-python-via-dotnet-24-5-release-notes/
Project-URL: Demos, https://products.aspose.app/svg/family
Project-URL: API Reference, https://reference.aspose.com/svg/python-net/
Project-URL: Examples, https://github.com/aspose-svg/Aspose.SVG-for-Python-via-.NET/
Project-URL: Blog, https://blog.aspose.com/category/svg/
Project-URL: Free Support, https://forum.aspose.com/c/svg
Project-URL: Temporary License, https://purchase.aspose.com/temporary-license
Keywords: Aspose,Aspose.SVG,Aspose.Total,Python,Component,Conholdate,Conholdate.Total,convert,converter,vectorization,vectorizer,vectorize,encoding,base64,css,DOM,dom-manipulation,image,JPEG,Library,Linux,macOS,Microsoft,mvc,net-standard,netcore,netstandard,to PDF,PNG,rotate,security,Standard,svg,svg-to-gif,svg-to-jpeg,svg-to-pdf,svg-to-png,svg-to-tiff,svg-to-xps,png-to-svg,jpg-to-svg,VisualStudio,XPath,XPS,SVG,Windows,Vector Graphics,line,B�zier Curves,Cubic,Glyphs,Paths,Text,Scaling,Rotation,S
Platform: win32
Classifier: Operating System :: Microsoft :: Windows
Classifier: License :: Other/Proprietary License
Classifier: Programming Language :: Python :: 3
Classifier: Programming Language :: Python :: 3 :: Only
Classifier: Programming Language :: Python :: 3.8
Classifier: Programming Language :: Python :: 3.9
Classifier: Programming Language :: Python :: 3.10
Classifier: Programming Language :: Python :: 3.11
Classifier: Topic :: Software Development :: Libraries
Classifier: Topic :: Office/Business
Classifier: Topic :: Office/Business :: Scheduling
Requires-Python: >=3.6,<3.12
